evolution/__init__.py
evolution/encoding/__init__.py
evolution/encoding/base.py
evolution/encoding/binary.py
evolution/encoding/gray.py
evolution/encoding/gray_code.py
evolution/encoding/interval.py
evolution/evolution.py
evolution/fitness.py
evolution/history/__init__.py
evolution/history/base.py
evolution/history/fitness.py
evolution/individual.py
evolution/metrics/__init__.py
evolution/metrics/base.py
evolution/metrics/fitness.py
evolution/population.py
evolution/selection/__init__.py
evolution/selection/base.py
evolution/selection/misc.py
evolution/selection/proportional2fitness.py
evolution/selection/proportional2inversefitness.py
evolution/selection/rank_based_exponential_classification.py
evolution/selection/rank_based_linear_classification.py
evolution/selection/roulette.py
evolution/selection/tournament.py
evolution/selection/uniform.py
evolution/variation/__init__.py
evolution/variation/crossover/__init__.py
evolution/variation/crossover/base.py
evolution/variation/crossover/bit.py
evolution/variation/crossover/cross_gen.py
evolution/variation/mutation/__init__.py
evolution/variation/mutation/base.py
evolution/variation/mutation/bit.py
evolution/variation/probability.py
cc521_evolution-1.1.2.dist-info/METADATA
cc521_evolution-1.1.2.dist-info/WHEEL
cc521_evolution-1.1.2.dist-info/RECORD
